{"Name":"navBar","Location":"top","Active":true,"Brand":"TXkgU3RvcmU=","BrandHTML":"","BrandLink":"/","Shade":"light","Background":"light","Style":"background-color: #e3f2fd;","StyleCSS":"","ShadeList":["dark","light","","","",""],"BackgroundList":["dark","light","","","",""],"MenuItemList":[{"Name":"Home","Link":"/"},{"Name":"Features","Link":"/pages/features"},{"Name":"New Products","Link":"/pages/NewProducts"},{"Name":"About","Link":"/pages/About"},{"Name":"","Link":""},{"Name":"","Link":""},{"Name":"","Link":""},{"Name":"","Link":""}]}